{
  "type": "FeatureCollection",
  "features": [
    {
      "type": "Feature",
      "properties": {
        "name": "Henry Dunant",
        "born": "Geneva, Switzerland"
      },
      "geometry": {
        "type": "Point",
        "coordinates": [
          6.15,
          46.2
        ]
      }
    },
    {
      "type": "Feature",
      "properties": {
        "name": "Emil Adolf von Behring",
        "born": "Hansdorf, Poland"
      },
      "geometry": {
        "type": "Point",
        "coordinates": [
          19.666667,
          53.6
        ]
      }
    },
    {
      "type": "Feature",
      "properties": {
        "name": "Wilhelm Röntgen",
        "born": "Lennep, Rhine Province, Germany"
      },
      "geometry": {
        "type": "Point",
        "coordinates": [
          7.2,
          51.183333
        ]
      }
    },
    {
      "type": "Feature",
      "properties": {
        "names": [
          "Sully Prudhomme",
          "Frédéric Passy"
        ],
        "born": "Paris, France"
      },
      "geometry": {
        "type": "Point",
        "coordinates": [
          2.3508,
          48.8567
        ]
      }
    },
    {
      "type": "Feature",
      "properties": {
        "name": "Jacobus Henricus van 't Hoff",
        "born": "Rotterdam, Netherlands"
      },
      "geometry": {
        "type": "Point",
        "coordinates": [
          4.5,
          51.916667
        ]
      }
    }
  ]
}